{"title":"alookso ─ 둘러보기 ─ 최신 글","url":"https://alook.so/discover/latest","favicon":"https://alook.so/assets/favicon/favicon-32x32-8fc0ef8efcf005e31acc7291922e138cf3d3654531e4556566ca5cc4797a6793.png","elements":[{"title":"이번 파도는 몇 번째일까 ?","contents":"<a class=\"text-lg text-gray-800 font-semibold line-clamp-2\" href=\"/posts/q1txzb\">이번 파도는 몇 번째일까 ?</a>","link":"https://alook.so/posts/q1txzb","retrieved":1643706934141},{"title":"밥 먹는 즐거움. 그리고 즐거움의 때(시기)","contents":"<a class=\"text-lg text-gray-800 font-semibold line-clamp-2\" href=\"/posts/Djtb8x\">밥 먹는 즐거움. 그리고 즐거움의 때(시기)</a>","link":"https://alook.so/posts/Djtb8x","retrieved":1643706934142},{"title":"마음의 중심.","contents":"<a class=\"text-lg text-gray-800 font-semibold line-clamp-2\" href=\"/posts/1Rtep8\">마음의 중심.</a>","link":"https://alook.so/posts/1Rtep8","retrieved":1643706934142},{"title":"답글: \"손님이 왕이다\"라는 말을 처음 만든 사람은 지옥에 갔을 것입니다.","contents":"<a class=\"text-lg text-gray-800 font-semibold line-clamp-2\" href=\"/posts/o7tGjV\">답글: \"손님이 왕이다\"라는 말을 처음 만든 사람은 지옥에 갔을 것입니다.</a>","link":"https://alook.so/posts/o7tGjV","retrieved":1643706934147},{"title":"듣기 싫은 뉴스는 없어서 좋네요.","contents":"<a class=\"text-lg text-gray-800 font-semibold line-clamp-2\" href=\"/posts/YytWJE\">듣기 싫은 뉴스는 없어서 좋네요.</a>","link":"https://alook.so/posts/YytWJE","retrieved":1643706934150},{"title":"30대가 생각하는 인맥.","contents":"<a class=\"text-lg text-gray-800 font-semibold line-clamp-2\" href=\"/posts/rDt3yb\">30대가 생각하는 인맥.</a>","link":"https://alook.so/posts/rDt3yb","retrieved":1643706934151},{"title":"군대, 병사의 머리 길이는 어느 정도가 적당할까요?","contents":"<a class=\"text-lg text-gray-800 font-semibold line-clamp-2\" href=\"/posts/jdt6vw\">군대, 병사의 머리 길이는 어느 정도가 적당할까요?</a>","link":"https://alook.so/posts/jdt6vw","retrieved":1643706934151}]}