{"title":"alookso ─ 둘러보기 ─ 최신 글","url":"https://alook.so/discover/latest","favicon":"https://alook.so/assets/favicon/favicon-32x32-8fc0ef8efcf005e31acc7291922e138cf3d3654531e4556566ca5cc4797a6793.png","elements":[{"title":"\"전세사기\" HUG도 보장못한다!!","contents":"<a class=\"text-lg text-gray-800 font-semibold line-clamp-2\" href=\"/posts/dzteD8\">\"전세사기\" HUG도 보장못한다!!</a>","link":"https://alook.so/posts/dzteD8","retrieved":1646810155090},{"title":"뭐 먹고 살지에 대한 고민","contents":"<a class=\"text-lg text-gray-800 font-semibold line-clamp-2\" href=\"/posts/pot035\">뭐 먹고 살지에 대한 고민 </a>","link":"https://alook.so/posts/pot035","retrieved":1646810155092},{"title":"건망증에 대하여...","contents":"<a class=\"text-lg text-gray-800 font-semibold line-clamp-2\" href=\"/posts/WLtmqq\">건망증에 대하여...</a>","link":"https://alook.so/posts/WLtmqq","retrieved":1646810155094}]}