{"title":"alookso ─ 둘러보기 ─ 최신 글","url":"https://alook.so/discover/latest","favicon":"https://alook.so/assets/favicon/favicon-32x32-8fc0ef8efcf005e31acc7291922e138cf3d3654531e4556566ca5cc4797a6793.png","elements":[{"title":"답글: 심려가 크시겠어요..","contents":"<a class=\"text-lg text-gray-800 font-semibold line-clamp-2\" href=\"/posts/Zkt53Y\">답글: 심려가 크시겠어요..</a>","link":"https://alook.so/posts/Zkt53Y","retrieved":1645258675132},{"title":"몸은 움직일수록 기분은 나아짐","contents":"<a class=\"text-lg text-gray-800 font-semibold line-clamp-2\" href=\"/posts/J5toly\">몸은 움직일수록 기분은 나아짐</a>","link":"https://alook.so/posts/J5toly","retrieved":1645258675134},{"title":"'발끈' 하던 사춘기 아들, 아빠 퇴근만 기다리는 이유","contents":"<a class=\"text-lg text-gray-800 font-semibold line-clamp-2\" href=\"/posts/potYrL\">﻿'발끈' 하던 사춘기 아들, 아빠 퇴근만 기다리는 이유</a>","link":"https://alook.so/posts/potYrL","retrieved":1645258675134},{"title":"요새 너무 게을러 졌어요 ㅜ","contents":"<a class=\"text-lg text-gray-800 font-semibold line-clamp-2\" href=\"/posts/PvtbaG\">요새 너무 게을러 졌어요 ㅜ</a>","link":"https://alook.so/posts/PvtbaG","retrieved":1645258675134},{"title":"38살 동생이 사표를 냈어요","contents":"<a class=\"text-lg text-gray-800 font-semibold line-clamp-2\" href=\"/posts/zvtmrd\">38살 동생이 사표를 냈어요</a>","link":"https://alook.so/posts/zvtmrd","retrieved":1645258675135}]}