{"title":"alookso ─ 둘러보기 ─ 최신 글","url":"https://alook.so/discover/latest","favicon":"https://alook.so/assets/favicon/favicon-32x32-8fc0ef8efcf005e31acc7291922e138cf3d3654531e4556566ca5cc4797a6793.png","elements":[{"title":"\"시간\" 어떻게쓰시나요","contents":"<a class=\"text-lg text-gray-800 font-semibold line-clamp-2\" href=\"/posts/WLt2Oa\">\"시간\" 어떻게쓰시나요</a>","link":"https://alook.so/posts/WLt2Oa","retrieved":1646133238411},{"title":"우울증으로 퇴사하는 나 자신이 너무 나약한 것 같아요.","contents":"<a class=\"text-lg text-gray-800 font-semibold line-clamp-2\" href=\"/posts/xlt4ny\">우울증으로 퇴사하는 나 자신이 너무 나약한 것 같아요.</a>","link":"https://alook.so/posts/xlt4ny","retrieved":1646133238414}]}