{"title":"alookso ─ 둘러보기 ─ 최신 글","url":"https://alook.so/discover/latest","favicon":"https://alook.so/assets/favicon/favicon-32x32-8fc0ef8efcf005e31acc7291922e138cf3d3654531e4556566ca5cc4797a6793.png","elements":[{"title":"원 기사에 부쳐 : 산재 단상","contents":"<a class=\"text-lg text-gray-800 font-semibold line-clamp-2\" href=\"/posts/jdto4X\">원 기사에 부쳐 : 산재 단상</a>","link":"https://alook.so/posts/jdto4X","retrieved":1646086558997},{"title":"감사합니다. 덕분입니다~","contents":"<a class=\"text-lg text-gray-800 font-semibold line-clamp-2\" href=\"/posts/Zkt3EY\">감사합니다. 덕분입니다~</a>","link":"https://alook.so/posts/Zkt3EY","retrieved":1646086558998},{"title":"[흘낏 책소개] 인간 불평등 기원론 - 장 자크 루소","contents":"<a class=\"text-lg text-gray-800 font-semibold line-clamp-2\" href=\"/posts/dztdLr\">[흘낏 책소개] 인간 불평등 기원론 - 장 자크 루소</a>","link":"https://alook.so/posts/dztdLr","retrieved":1646086558999}]}