{"title":"alookso ─ 둘러보기 ─ 최신 글","url":"https://alook.so/discover/latest","favicon":"https://alook.so/assets/favicon/favicon-32x32-8fc0ef8efcf005e31acc7291922e138cf3d3654531e4556566ca5cc4797a6793.png","elements":[{"title":"저는 이곳에 투자합니다.","contents":"<a class=\"text-lg text-gray-800 font-semibold line-clamp-2\" href=\"/posts/njt49Z\">저는 이곳에 투자합니다.</a>","link":"https://alook.so/posts/njt49Z","retrieved":1644462944070},{"title":"늙었나 보다","contents":"<a class=\"text-lg text-gray-800 font-semibold line-clamp-2\" href=\"/posts/3wt5W0\">늙었나 보다</a>","link":"https://alook.so/posts/3wt5W0","retrieved":1644462944076},{"title":"유가 상승은 언제까지 일까?","contents":"<a class=\"text-lg text-gray-800 font-semibold line-clamp-2\" href=\"/posts/8Wtem9\">유가 상승은 언제까지 일까?</a>","link":"https://alook.so/posts/8Wtem9","retrieved":1644462944076},{"title":"노래가 주는 힘이 이런게 아닐까요","contents":"<a class=\"text-lg text-gray-800 font-semibold line-clamp-2\" href=\"/posts/G1tDRL\">노래가 주는 힘이 이런게 아닐까요</a>","link":"https://alook.so/posts/G1tDRL","retrieved":1644462944077},{"title":"하루하루 좋아지는걸 느낄때","contents":"<a class=\"text-lg text-gray-800 font-semibold line-clamp-2\" href=\"/posts/E7tOvK\">하루하루 좋아지는걸 느낄때</a>","link":"https://alook.so/posts/E7tOvK","retrieved":1644462944078},{"title":"퇴직을 앞두고...이런 상사가 되어주세요. 7","contents":"<a class=\"text-lg text-gray-800 font-semibold line-clamp-2\" href=\"/posts/92tPY8\">퇴직을 앞두고...이런 상사가 되어주세요. 7</a>","link":"https://alook.so/posts/92tPY8","retrieved":1644462944079}]}