{"title":"alookso ─ 둘러보기 ─ 최신 글","url":"https://alook.so/discover/latest","favicon":"https://alook.so/assets/favicon/favicon-32x32-8fc0ef8efcf005e31acc7291922e138cf3d3654531e4556566ca5cc4797a6793.png","elements":[{"title":"나에게 친구란 잊혀져 가는 투명 인간","contents":"<a class=\"text-lg text-gray-800 font-semibold line-clamp-2\" href=\"/posts/latXjD\">나에게 친구란 잊혀져 가는 투명 인간</a>","link":"https://alook.so/posts/latXjD","retrieved":1644938033187},{"title":"답글: 오미크론이 계절 독감 수준으로 관리되기 위한 조건","contents":"<a class=\"text-lg text-gray-800 font-semibold line-clamp-2\" href=\"/posts/92t2EL\">답글: 오미크론이 계절 독감 수준으로 관리되기 위한 조건</a>","link":"https://alook.so/posts/92t2EL","retrieved":1644938033187},{"title":"우크라이나에 희망이 보이는걸까","contents":"<a class=\"text-lg text-gray-800 font-semibold line-clamp-2\" href=\"/posts/mbtKxz\">우크라이나에 희망이 보이는걸까 </a>","link":"https://alook.so/posts/mbtKxz","retrieved":1644938033191},{"title":"돈을 못 버는 직업...","contents":"<a class=\"text-lg text-gray-800 font-semibold line-clamp-2\" href=\"/posts/54tGnE\">돈을 못 버는 직업...</a>","link":"https://alook.so/posts/54tGnE","retrieved":1644938033191},{"title":"아이들을 지켜주세요.","contents":"<a class=\"text-lg text-gray-800 font-semibold line-clamp-2\" href=\"/posts/q1tkq1\">아이들을 지켜주세요.</a>","link":"https://alook.so/posts/q1tkq1","retrieved":1644938033191},{"title":"후원은 이렇게 하는 것이 맞을까요??","contents":"<a class=\"text-lg text-gray-800 font-semibold line-clamp-2\" href=\"/posts/DjtDdK\">후원은 이렇게 하는 것이 맞을까요??</a>","link":"https://alook.so/posts/DjtDdK","retrieved":1644938033191},{"title":"한국, 해외에서도 이젠 위험지역으로 분류","contents":"<a class=\"text-lg text-gray-800 font-semibold line-clamp-2\" href=\"/posts/o7tDdR\">한국, 해외에서도 이젠 위험지역으로 분류</a>","link":"https://alook.so/posts/o7tDdR","retrieved":1644938033193}]}