{"title":"alookso ─ 둘러보기 ─ 최신 글","url":"https://alook.so/discover/latest","favicon":"https://alook.so/assets/favicon/favicon-32x32-8fc0ef8efcf005e31acc7291922e138cf3d3654531e4556566ca5cc4797a6793.png","elements":[{"title":"한국, 자살률 1위 벗어나기 위해 핀란드를 참고해보자","contents":"<a class=\"text-lg text-gray-800 font-semibold line-clamp-2\" href=\"/posts/rDt0W9\">한국, 자살률 1위 벗어나기 위해 핀란드를 참고해보자</a>","link":"https://alook.so/posts/rDt0W9","retrieved":1642425952612},{"title":"새로운 먹거리  NFT, 메타버스?","contents":"<a class=\"text-lg text-gray-800 font-semibold line-clamp-2\" href=\"/posts/jdtEBl\">새로운 먹거리  NFT, 메타버스?</a>","link":"https://alook.so/posts/jdtEBl","retrieved":1642425952612},{"title":"☆올해부터 바뀐 우회전시 도로교통법규","contents":"<a class=\"text-lg text-gray-800 font-semibold line-clamp-2\" href=\"/posts/a0t0Rx\">☆올해부터 바뀐 우회전시 도로교통법규</a>","link":"https://alook.so/posts/a0t0Rx","retrieved":1642425952613},{"title":"LG에너지솔루션.... 공모주의 명 과 암!","contents":"<a class=\"text-lg text-gray-800 font-semibold line-clamp-2\" href=\"/posts/dztlPo\">LG에너지솔루션.... 공모주의 명 과 암! </a>","link":"https://alook.so/posts/dztlPo","retrieved":1642425952615},{"title":"애매한 재능","contents":"<a class=\"text-lg text-gray-800 font-semibold line-clamp-2\" href=\"/posts/J5tV3r\">애매한 재능</a>","link":"https://alook.so/posts/J5tV3r","retrieved":1642425952617},{"title":"[오늘의 한잔] 무엇을 먹을꼬!","contents":"<a class=\"text-lg text-gray-800 font-semibold line-clamp-2\" href=\"/posts/Pvtp9r\">[오늘의 한잔] 무엇을 먹을꼬!</a>","link":"https://alook.so/posts/Pvtp9r","retrieved":1642425952617}]}