{"title":"alookso ─ 둘러보기 ─ 뜨는 글","url":"https://alook.so/discover","favicon":"https://alook.so/assets/favicon/favicon-32x32-8fc0ef8efcf005e31acc7291922e138cf3d3654531e4556566ca5cc4797a6793.png","elements":[{"title":"악플에 대한 유튜버의 생각","contents":"<a class=\"text-lg text-gray-800 font-semibold line-clamp-2\" href=\"/posts/KmtYjK\">악플에 대한 유튜버의 생각</a>","link":"https://alook.so/posts/KmtYjK","retrieved":1644138897755},{"title":"여러분은 어떤 꿈을 가지고 사시나요?","contents":"<a class=\"text-lg text-gray-800 font-semibold line-clamp-2\" href=\"/posts/2xtX4P\">여러분은 어떤 꿈을 가지고 사시나요?</a>","link":"https://alook.so/posts/2xtX4P","retrieved":1644135423619},{"title":"제가 너무 발칙하고 못된 건가요?","contents":"<a class=\"text-lg text-gray-800 font-semibold line-clamp-2\" href=\"/posts/4Xtd5d\">제가 너무 발칙하고 못된 건가요?</a>","link":"https://alook.so/posts/4Xtd5d","retrieved":1644128284367},{"title":"답글: 인상이 깊은 글이네요.","contents":"<a class=\"text-lg text-gray-800 font-semibold line-clamp-2\" href=\"/posts/kZtPz7\">답글: 인상이 깊은 글이네요.</a>","link":"https://alook.so/posts/kZtPz7","retrieved":1644138897782},{"title":"일기 쓰시나요?","contents":"<a class=\"text-lg text-gray-800 font-semibold line-clamp-2\" href=\"/posts/lat3ma\">일기 쓰시나요?</a>","link":"https://alook.so/posts/lat3ma","retrieved":1644128284367},{"title":"[무(비)드(라마)Q(레이션)] 시간여행","contents":"<a class=\"text-lg text-gray-800 font-semibold line-clamp-2\" href=\"/posts/mbtZya\">[무(비)드(라마)Q(레이션)] 시간여행</a>","link":"https://alook.so/posts/mbtZya","retrieved":1644135423617},{"title":"[늦은 아침 생각] 이익이 되는 협동, 상호성, 용서","contents":"<a class=\"text-lg text-gray-800 font-semibold line-clamp-2\" href=\"/posts/0ktwyZ\">[늦은 아침 생각] 이익이 되는 협동, 상호성, 용서</a>","link":"https://alook.so/posts/0ktwyZ","retrieved":1644117306824},{"title":"얼룩소 인연에 관한 이야기","contents":"<a class=\"text-lg text-gray-800 font-semibold line-clamp-2\" href=\"/posts/njtk7M\">얼룩소 인연에 관한 이야기</a>","link":"https://alook.so/posts/njtk7M","retrieved":1644117306821}]}