{"title":"alookso ─ 둘러보기 ─ 뜨는 글","url":"https://alook.so/discover/latest","favicon":"https://alook.so/assets/favicon/favicon-32x32-8fc0ef8efcf005e31acc7291922e138cf3d3654531e4556566ca5cc4797a6793.png","elements":[{"title":"실수하면 좋은 일이 일어납니다.","contents":"<a class=\"text-lg text-gray-800 font-semibold line-clamp-2\" href=\"/posts/Djt3e2D\">실수하면 좋은 일이 일어납니다.</a>","link":"https://alook.so/posts/Djt3e2D","retrieved":1649161626795},{"title":"애도하는 사람","contents":"<a class=\"text-lg text-gray-800 font-semibold line-clamp-2\" href=\"/posts/1RtJ7k7\">애도하는 사람</a>","link":"https://alook.so/posts/1RtJ7k7","retrieved":1649161626800},{"title":"나는 적립식으로 꾸준히 모아가는  투자를 하고 있다","contents":"<a class=\"text-lg text-gray-800 font-semibold line-clamp-2\" href=\"/posts/eVtM1aR\">나는 적립식으로 꾸준히 모아가는  투자를 하고 있다</a>","link":"https://alook.so/posts/eVtM1aR","retrieved":1649153821134},{"title":"나는 몇 살 까지 일 할 수 있을까?","contents":"<a class=\"text-lg text-gray-800 font-semibold line-clamp-2\" href=\"/posts/8Wtw0v8\">나는 몇 살 까지 일 할 수 있을까?</a>","link":"https://alook.so/posts/8Wtw0v8","retrieved":1649153821139},{"title":"\"야호~~\" 메아리로 답해보는 글.","contents":"<a class=\"text-lg text-gray-800 font-semibold line-clamp-2\" href=\"/posts/E7t7RbR\">\"야호~~\" 메아리로 답해보는 글.</a>","link":"https://alook.so/posts/E7t7RbR","retrieved":1649153821138},{"title":"식목일 - 사라져가는 나무와 식물들, 우리의 미래는?","contents":"<a class=\"text-lg text-gray-800 font-semibold line-clamp-2\" href=\"/posts/yEtELRo\">식목일 - 사라져가는 나무와 식물들, 우리의 미래는?</a>","link":"https://alook.so/posts/yEtELRo","retrieved":1649150192813},{"title":"혼자 살아보니..","contents":"<a class=\"text-lg text-gray-800 font-semibold line-clamp-2\" href=\"/posts/q1tGwkl\">혼자 살아보니..</a>","link":"https://alook.so/posts/q1tGwkl","retrieved":1649146840236},{"title":"이번에도 최저임금 결정은 쉽지 않겠네요","contents":"<a class=\"text-lg text-gray-800 font-semibold line-clamp-2\" href=\"/posts/xltoYM8\">이번에도 최저임금 결정은 쉽지 않겠네요</a>","link":"https://alook.so/posts/xltoYM8","retrieved":1649146840258},{"title":"얼룩소에게","contents":"<a class=\"text-lg text-gray-800 font-semibold line-clamp-2\" href=\"/posts/eVtM1mD\">얼룩소에게</a>","link":"https://alook.so/posts/eVtM1mD","retrieved":1649142996728},{"title":"이 곳이 공론의 장이자, 소통의 공간이자, 힐링의 공간이 되기를 바라며.......","contents":"<a class=\"text-lg text-gray-800 font-semibold line-clamp-2\" href=\"/posts/kZtBKmk\">이 곳이 공론의 장이자, 소통의 공간이자, 힐링의 공간이 되기를 바라며.......</a>","link":"https://alook.so/posts/kZtBKmk","retrieved":1649142996760},{"title":"이제 그만 하겠습니다","contents":"<a class=\"text-lg text-gray-800 font-semibold line-clamp-2\" href=\"/posts/XBtXOV3\">이제 그만 하겠습니다</a>","link":"https://alook.so/posts/XBtXOV3","retrieved":1649142996760},{"title":"얼룩소에 아무리 투자에 대해 조언해봐야..대부분 의미가 없겠지만...나 자신에게 도움이 된다","contents":"<a class=\"text-lg text-gray-800 font-semibold line-clamp-2\" href=\"/posts/o7tnBEb\">얼룩소에 아무리 투자에 대해 조언해봐야..대부분 의미가 없겠지만...나 자신에게 도움이 된다</a>","link":"https://alook.so/posts/o7tnBEb","retrieved":1649139670633},{"title":"대중교통으로 출퇴근하기","contents":"<a class=\"text-lg text-gray-800 font-semibold line-clamp-2\" href=\"/posts/XBtXOdv\">대중교통으로 출퇴근하기</a>","link":"https://alook.so/posts/XBtXOdv","retrieved":1649139670633},{"title":"답글: '공론'이란 무엇일까요","contents":"<a class=\"text-lg text-gray-800 font-semibold line-clamp-2\" href=\"/posts/J5tOe9Y\">답글: '공론'이란 무엇일까요</a>","link":"https://alook.so/posts/J5tOe9Y","retrieved":1649132451271},{"title":"메아리 없는 야호-","contents":"<a class=\"text-lg text-gray-800 font-semibold line-clamp-2\" href=\"/posts/6MtYbmR\">메아리 없는 야호-</a>","link":"https://alook.so/posts/6MtYbmR","retrieved":1649127238935},{"title":"반응이 낮으면 공론도 되지 않는.","contents":"<a class=\"text-lg text-gray-800 font-semibold line-clamp-2\" href=\"/posts/yEtELBK\">반응이 낮으면 공론도 되지 않는. </a>","link":"https://alook.so/posts/yEtELBK","retrieved":1649110582221},{"title":"돈자랑만 하는 친구","contents":"<a class=\"text-lg text-gray-800 font-semibold line-clamp-2\" href=\"/posts/8WtwLYy\">돈자랑만 하는 친구</a>","link":"https://alook.so/posts/8WtwLYy","retrieved":1649075335372},{"title":"어떤 죽음","contents":"<a class=\"text-lg text-gray-800 font-semibold line-clamp-2\" href=\"/posts/jdtd0oX\">어떤 죽음</a>","link":"https://alook.so/posts/jdtd0oX","retrieved":1649075335373}]}